alterlab/__init__.py
alterlab/client.py
alterlab-2.0.1.dist-info/METADATA
alterlab-2.0.1.dist-info/WHEEL
alterlab-2.0.1.dist-info/RECORD
